extract_design/__init__.py
extract_design/client.py
extract_design/errors.py
extract_design/types.py
extract_design-0.1.0.dist-info/METADATA
extract_design-0.1.0.dist-info/WHEEL
extract_design-0.1.0.dist-info/licenses/LICENSE
extract_design-0.1.0.dist-info/RECORD
