Metadata-Version: 2.4
Name: extract-design
Version: 0.1.0
Summary: Official Python SDK for the extract.design API
Project-URL: Homepage, https://extract.design
Project-URL: Documentation, https://extract.design/docs
Project-URL: Repository, https://github.com/pixelgenesis/extract-design-python
Project-URL: Issues, https://github.com/pixelgenesis/extract-design-python/issues
Author-email: Pixel Genesis LLC <support@extract.design>
License-Expression: MIT
License-File: LICENSE
Keywords: ai,api,background-removal,design,extract.design,pod,print-on-demand,sdk
Classifier: Development Status :: 4 - Beta
Classifier: Intended Audience :: Developers
Classifier: License :: OSI Approved :: MIT License
Classifier: Operating System :: OS Independent
Classifier: Programming Language :: Python :: 3
Classifier: Programming Language :: Python :: 3.10
Classifier: Programming Language :: Python :: 3.11
Classifier: Programming Language :: Python :: 3.12
Classifier: Programming Language :: Python :: 3.13
Classifier: Topic :: Software Development :: Libraries :: Python Modules
Classifier: Typing :: Typed
Requires-Python: >=3.10
Requires-Dist: httpx>=0.25.0
Provides-Extra: dev
Requires-Dist: pyright>=1.1.0; extra == 'dev'
Requires-Dist: pytest-httpx>=0.30.0; extra == 'dev'
Requires-Dist: pytest>=7.0.0; extra == 'dev'
Requires-Dist: ruff>=0.1.0; extra == 'dev'
